fastapi_identity_sqlalchemy/__init__.py
fastapi_identity_sqlalchemy/db_context.py
fastapi_identity_sqlalchemy/exc.py
fastapi_identity_sqlalchemy/models.py
fastapi_identity_sqlalchemy/stores.py
fastapi_identity_sqlalchemy/types.py
fastapi_identity_sqlalchemy-1.0.5.dist-info/METADATA
fastapi_identity_sqlalchemy-1.0.5.dist-info/WHEEL
fastapi_identity_sqlalchemy-1.0.5.dist-info/top_level.txt
fastapi_identity_sqlalchemy-1.0.5.dist-info/RECORD
