Metadata-Version: 2.1
Name: fastapi-identity-sqlalchemy
Version: 1.0.5
Requires-Dist: sqlalchemy
